{
  "$id": "urn:groupsum:schemaorg:class:HowToSupply",
  "$schema": "https://json-schema.org/draft/2020-12/schema",
  "allOf": [
    {
      "$ref": "HowToItem.schema.json"
    },
    {
      "properties": {
        "@context": {
          "const": "https://schema.org"
        },
        "@type": {
          "const": "HowToSupply"
        },
        "estimatedCost": {
          "$ref": "../properties/estimatedCost.schema.json",
          "description": "The estimated cost of the supply or supplies consumed when performing instructions."
        }
      },
      "required": [
        "@type"
      ],
      "type": "object",
      "unevaluatedProperties": false,
      "x-schemaorg-cardinality": "open-world"
    }
  ],
  "description": "A supply consumed when performing the instructions for how to achieve a result.",
  "title": "HowToSupply"
}
