{
  "$id": "urn:groupsum:schemaorg:class:PublicationIssue",
  "$schema": "https://json-schema.org/draft/2020-12/schema",
  "allOf": [
    {
      "$ref": "CreativeWork.schema.json"
    },
    {
      "properties": {
        "@context": {
          "const": "https://schema.org"
        },
        "@type": {
          "const": "PublicationIssue"
        },
        "issueNumber": {
          "$ref": "../properties/issueNumber.schema.json",
          "description": "Identifies the issue of publication; for example, \"iii\" or \"2\"."
        },
        "pageEnd": {
          "$ref": "../properties/pageEnd.schema.json",
          "description": "The page on which the work ends; for example \"138\" or \"xvi\"."
        },
        "pageStart": {
          "$ref": "../properties/pageStart.schema.json",
          "description": "The page on which the work starts; for example \"135\" or \"xiii\"."
        },
        "pagination": {
          "$ref": "../properties/pagination.schema.json",
          "description": "Any description of pages that is not separated into pageStart and pageEnd; for example, \"1-6, 9, 55\" or \"10-12, 46-49\"."
        }
      },
      "required": [
        "@type"
      ],
      "type": "object",
      "unevaluatedProperties": false,
      "x-schemaorg-cardinality": "open-world"
    }
  ],
  "description": "A part of a successively published publication such as a periodical or publication volume, often numbered, usually containing a grouping of works such as articles.\\n\\nSee also [blog post](https://blog-schema.org/2014/09/02/schema-org-support-for-bibliographic-relationships-and-periodicals/).",
  "title": "PublicationIssue"
}
