{
  "$id": "urn:groupsum:schemaorg:class:SatiricalArticle",
  "$schema": "https://json-schema.org/draft/2020-12/schema",
  "allOf": [
    {
      "$ref": "Article.schema.json"
    },
    {
      "properties": {
        "@context": {
          "const": "https://schema.org"
        },
        "@type": {
          "const": "SatiricalArticle"
        }
      },
      "required": [
        "@type"
      ],
      "type": "object",
      "unevaluatedProperties": false,
      "x-schemaorg-cardinality": "open-world"
    }
  ],
  "description": "An [[Article]] whose content is primarily [[satirical]](https://en.wikipedia.org/wiki/Satire) in nature, i.e. unlikely to be literally true. A satirical article is sometimes but not necessarily also a [[NewsArticle]]. [[ScholarlyArticle]]s are also sometimes satirized.",
  "title": "SatiricalArticle"
}
