{
  "$id": "urn:groupsum:schemaorg:class:XPathType",
  "$schema": "https://json-schema.org/draft/2020-12/schema",
  "allOf": [
    {
      "$ref": "../datatypes/Text.schema.json"
    },
    {
      "properties": {
        "@context": {
          "const": "https://schema.org"
        },
        "@type": {
          "const": "XPathType"
        }
      },
      "required": [
        "@type"
      ],
      "type": "object",
      "unevaluatedProperties": false,
      "x-schemaorg-cardinality": "open-world"
    }
  ],
  "description": "Text representing an XPath (typically but not necessarily version 1.0).",
  "title": "XPathType"
}
