{
  "$id": "urn:groupsum:schemaorg:property:adverseOutcome",
  "$ref": "../types/MedicalEntity.schema.json",
  "$schema": "https://json-schema.org/draft/2020-12/schema",
  "description": "A possible complication and/or side effect of this therapy. If it is known that an adverse outcome is serious (resulting in death, disability, or permanent damage; requiring hospitalization; or otherwise life-threatening or requiring immediate medical attention), tag it as a seriousAdverseOutcome instead.",
  "title": "adverseOutcome",
  "x-schemaorg-cardinality": "open-world"
}
